{"response":{"periods":{"months":"current","report":"not_current","visibility":"not_current","semester":"not_current"},"days":[1,2,3,4,5,6,7,8,9,10,11,12,13,14,15,16,17,18,19,20,21,22,23,24,25,26,27,28,29,30,31],"subjects":{"\u0410\u043b\u0433\u0435\u0431\u0440\u0430":[[{"key":"day","value":1},{"key":"mark","value":11}],[{"key":"day","value":2},{"key":"mark","value":3},{"key":"comment","value":"\u0437\u0430\u043c\u0435\u0447\u0430\u043d\u0438\u0435 \u043d\u0430 \u0443\u0440\u043e\u043a\u0435"}],[{"key":"day","value":3},{"key":"mark","value":5},{"key":"comment","value":"\u0437\u0430\u043c\u0435\u0447\u0430\u043d\u0438\u0435 \u043d\u0430 \u0443\u0440\u043e\u043a\u0435"}],[{"key":"day","value":4},{"key":"mark","value":5}],[{"key":"day","value":6},{"key":"mark","value":10},{"key":"comment","value":"\u0437\u0430\u043c\u0435\u0447\u0430\u043d\u0438\u0435 \u043d\u0430 \u0443\u0440\u043e\u043a\u0435"}],[{"key":"day","value":7},{"key":"mark","value":12}],[{"key":"day","value":8},{"key":"mark","value":5},{"key":"comment","value":"\u0437\u0430\u043c\u0435\u0447\u0430\u043d\u0438\u0435 \u043d\u0430 \u0443\u0440\u043e\u043a\u0435"}],[{"key":"day","value":9},{"key":"mark","value":9},{"key":"comment","value":"\u0437\u0430\u043c\u0435\u0447\u0430\u043d\u0438\u0435 \u043d\u0430 \u0443\u0440\u043e\u043a\u0435"}],[{"key":"day","value":10},{"key":"mark","value":3}],[{"key":"day","value":15},{"key":"mark","value":9},{"key":"comment","value":"\u0437\u0430\u043c\u0435\u0447\u0430\u043d\u0438\u0435 \u043d\u0430 \u0443\u0440\u043e\u043a\u0435"}],[{"key":"day","value":17},{"key":"mark","value":1},{"key":"comment","value":"\u0437\u0430\u043c\u0435\u0447\u0430\u043d\u0438\u0435 \u043d\u0430 \u0443\u0440\u043e\u043a\u0435"}],[{"key":"day","value":19},{"key":"mark","value":9}],[{"key":"day","value":20},{"key":"mark","value":5},{"key":"comment","value":"\u0437\u0430\u043c\u0435\u0447\u0430\u043d\u0438\u0435 \u043d\u0430 \u0443\u0440\u043e\u043a\u0435"}],[{"key":"day","value":25},{"key":"mark","value":10},{"key":"comment","value":"\u0437\u0430\u043c\u0435\u0447\u0430\u043d\u0438\u0435 \u043d\u0430 \u0443\u0440\u043e\u043a\u0435"}],[{"key":"day","value":26},{"key":"mark","value":12},{"key":"comment","value":"\u0437\u0430\u043c\u0435\u0447\u0430\u043d\u0438\u0435 \u043d\u0430 \u0443\u0440\u043e\u043a\u0435"}],[{"key":"day","value":27},{"key":"mark","value":9}],[{"key":"day","value":31},{"key":"mark","value":12},{"key":"comment","value":"\u0437\u0430\u043c\u0435\u0447\u0430\u043d\u0438\u0435 \u043d\u0430 \u0443\u0440\u043e\u043a\u0435"}]],"\u0410\u043d\u0433\u043b\u0456\u0439\u0441\u044c\u043a\u0430":[[{"key":"day","value":1},{"key":"mark","value":12}],[{"key":"day","value":5},{"key":"mark","value":8}],[{"key":"day","value":6},{"key":"mark","value":6}],[{"key":"day","value":7},{"key":"mark","value":10}],[{"key":"day","value":9},{"key":"mark","value":4},{"key":"comment","value":"\u0437\u0430\u043c\u0435\u0447\u0430\u043d\u0438\u0435 \u043d\u0430 \u0443\u0440\u043e\u043a\u0435"}],[{"key":"day","value":10},{"key":"mark","value":9}],[{"key":"day","value":11},{"key":"mark","value":6},{"key":"comment","value":"\u0437\u0430\u043c\u0435\u0447\u0430\u043d\u0438\u0435 \u043d\u0430 \u0443\u0440\u043e\u043a\u0435"}],[{"key":"day","value":13},{"key":"mark","value":2},{"key":"comment","value":"\u0437\u0430\u043c\u0435\u0447\u0430\u043d\u0438\u0435 \u043d\u0430 \u0443\u0440\u043e\u043a\u0435"}],[{"key":"day","value":17},{"key":"mark","value":7},{"key":"comment","value":"\u0437\u0430\u043c\u0435\u0447\u0430\u043d\u0438\u0435 \u043d\u0430 \u0443\u0440\u043e\u043a\u0435"}],[{"key":"day","value":19},{"key":"mark","value":4},{"key":"comment","value":"\u0437\u0430\u043c\u0435\u0447\u0430\u043d\u0438\u0435 \u043d\u0430 \u0443\u0440\u043e\u043a\u0435"}],[{"key":"day","value":20},{"key":"mark","value":1}],[{"key":"day","value":21},{"key":"mark","value":2}],[{"key":"day","value":22},{"key":"mark","value":9},{"key":"comment","value":"\u0437\u0430\u043c\u0435\u0447\u0430\u043d\u0438\u0435 \u043d\u0430 \u0443\u0440\u043e\u043a\u0435"}],[{"key":"day","value":25},{"key":"mark","value":1},{"key":"comment","value":"\u0437\u0430\u043c\u0435\u0447\u0430\u043d\u0438\u0435 \u043d\u0430 \u0443\u0440\u043e\u043a\u0435"}],[{"key":"day","value":27},{"key":"mark","value":4},{"key":"comment","value":"\u0437\u0430\u043c\u0435\u0447\u0430\u043d\u0438\u0435 \u043d\u0430 \u0443\u0440\u043e\u043a\u0435"}],[{"key":"day","value":28},{"key":"mark","value":11}]],"\u0410\u0441\u0442\u0440\u043e\u043d\u043e\u043c\u0456\u044f":[[{"key":"day","value":1},{"key":"mark","value":6},{"key":"comment","value":"\u0437\u0430\u043c\u0435\u0447\u0430\u043d\u0438\u0435 \u043d\u0430 \u0443\u0440\u043e\u043a\u0435"}],[{"key":"day","value":2},{"key":"mark","value":12},{"key":"comment","value":"\u0437\u0430\u043c\u0435\u0447\u0430\u043d\u0438\u0435 \u043d\u0430 \u0443\u0440\u043e\u043a\u0435"}],[{"key":"day","value":3},{"key":"mark","value":12}],[{"key":"day","value":5},{"key":"mark","value":10}],[{"key":"day","value":7},{"key":"mark","value":3}],[{"key":"day","value":8},{"key":"mark","value":4}],[{"key":"day","value":11},{"key":"mark","value":4}],[{"key":"day","value":15},{"key":"mark","value":4}],[{"key":"day","value":16},{"key":"mark","value":9},{"key":"comment","value":"\u0437\u0430\u043c\u0435\u0447\u0430\u043d\u0438\u0435 \u043d\u0430 \u0443\u0440\u043e\u043a\u0435"}],[{"key":"day","value":19},{"key":"mark","value":1}],[{"key":"day","value":20},{"key":"mark","value":2}],[{"key":"day","value":23},{"key":"mark","value":5},{"key":"comment","value":"\u0437\u0430\u043c\u0435\u0447\u0430\u043d\u0438\u0435 \u043d\u0430 \u0443\u0440\u043e\u043a\u0435"}],[{"key":"day","value":28},{"key":"mark","value":10}],[{"key":"day","value":30},{"key":"mark","value":10}]],"\u0413\u0435\u043e\u043c\u0435\u0442\u0440\u0456\u044f":[[{"key":"day","value":2},{"key":"mark","value":10},{"key":"comment","value":"\u0437\u0430\u043c\u0435\u0447\u0430\u043d\u0438\u0435 \u043d\u0430 \u0443\u0440\u043e\u043a\u0435"}],[{"key":"day","value":4},{"key":"mark","value":9}],[{"key":"day","value":7},{"key":"mark","value":2}],[{"key":"day","value":10},{"key":"mark","value":9}],[{"key":"day","value":12},{"key":"mark","value":3},{"key":"comment","value":"\u0437\u0430\u043c\u0435\u0447\u0430\u043d\u0438\u0435 \u043d\u0430 \u0443\u0440\u043e\u043a\u0435"}],[{"key":"day","value":13},{"key":"mark","value":5},{"key":"comment","value":"\u0437\u0430\u043c\u0435\u0447\u0430\u043d\u0438\u0435 \u043d\u0430 \u0443\u0440\u043e\u043a\u0435"}],[{"key":"day","value":14},{"key":"mark","value":8}],[{"key":"day","value":16},{"key":"mark","value":5}],[{"key":"day","value":17},{"key":"mark","value":12}],[{"key":"day","value":19},{"key":"mark","value":3},{"key":"comment","value":"\u0437\u0430\u043c\u0435\u0447\u0430\u043d\u0438\u0435 \u043d\u0430 \u0443\u0440\u043e\u043a\u0435"}],[{"key":"day","value":20},{"key":"mark","value":1}],[{"key":"day","value":21},{"key":"mark","value":5},{"key":"comment","value":"\u0437\u0430\u043c\u0435\u0447\u0430\u043d\u0438\u0435 \u043d\u0430 \u0443\u0440\u043e\u043a\u0435"}],[{"key":"day","value":24},{"key":"mark","value":12}],[{"key":"day","value":27},{"key":"mark","value":1},{"key":"comment","value":"\u0437\u0430\u043c\u0435\u0447\u0430\u043d\u0438\u0435 \u043d\u0430 \u0443\u0440\u043e\u043a\u0435"}],[{"key":"day","value":29},{"key":"mark","value":6}],[{"key":"day","value":30},{"key":"mark","value":1},{"key":"comment","value":"\u0437\u0430\u043c\u0435\u0447\u0430\u043d\u0438\u0435 \u043d\u0430 \u0443\u0440\u043e\u043a\u0435"}]],"\u0416\u0438\u0432\u043e\u043f\u0438\u0441":[[{"key":"day","value":1},{"key":"mark","value":11}],[{"key":"day","value":6},{"key":"mark","value":8}],[{"key":"day","value":7},{"key":"mark","value":4},{"key":"comment","value":"\u0437\u0430\u043c\u0435\u0447\u0430\u043d\u0438\u0435 \u043d\u0430 \u0443\u0440\u043e\u043a\u0435"}],[{"key":"day","value":8},{"key":"mark","value":8}],[{"key":"day","value":9},{"key":"mark","value":11}],[{"key":"day","value":11},{"key":"mark","value":6},{"key":"comment","value":"\u0437\u0430\u043c\u0435\u0447\u0430\u043d\u0438\u0435 \u043d\u0430 \u0443\u0440\u043e\u043a\u0435"}],[{"key":"day","value":12},{"key":"mark","value":8}],[{"key":"day","value":13},{"key":"mark","value":11},{"key":"comment","value":"\u0437\u0430\u043c\u0435\u0447\u0430\u043d\u0438\u0435 \u043d\u0430 \u0443\u0440\u043e\u043a\u0435"}],[{"key":"day","value":16},{"key":"mark","value":5},{"key":"comment","value":"\u0437\u0430\u043c\u0435\u0447\u0430\u043d\u0438\u0435 \u043d\u0430 \u0443\u0440\u043e\u043a\u0435"}],[{"key":"day","value":17},{"key":"mark","value":6}],[{"key":"day","value":18},{"key":"mark","value":7},{"key":"comment","value":"\u0437\u0430\u043c\u0435\u0447\u0430\u043d\u0438\u0435 \u043d\u0430 \u0443\u0440\u043e\u043a\u0435"}],[{"key":"day","value":21},{"key":"mark","value":6},{"key":"comment","value":"\u0437\u0430\u043c\u0435\u0447\u0430\u043d\u0438\u0435 \u043d\u0430 \u0443\u0440\u043e\u043a\u0435"}],[{"key":"day","value":23},{"key":"mark","value":4}],[{"key":"day","value":25},{"key":"mark","value":2}],[{"key":"day","value":26},{"key":"mark","value":12}],[{"key":"day","value":27},{"key":"mark","value":8}],[{"key":"day","value":29},{"key":"mark","value":10}]],"\u0406\u043d\u043e\u0437\u0435\u043c\u043d\u0430 \u043c\u043e\u0432\u0430":[[{"key":"day","value":1},{"key":"mark","value":1},{"key":"comment","value":"\u0437\u0430\u043c\u0435\u0447\u0430\u043d\u0438\u0435 \u043d\u0430 \u0443\u0440\u043e\u043a\u0435"}],[{"key":"day","value":3},{"key":"mark","value":10}],[{"key":"day","value":7},{"key":"mark","value":11},{"key":"comment","value":"\u0437\u0430\u043c\u0435\u0447\u0430\u043d\u0438\u0435 \u043d\u0430 \u0443\u0440\u043e\u043a\u0435"}],[{"key":"day","value":8},{"key":"mark","value":12},{"key":"comment","value":"\u0437\u0430\u043c\u0435\u0447\u0430\u043d\u0438\u0435 \u043d\u0430 \u0443\u0440\u043e\u043a\u0435"}],[{"key":"day","value":9},{"key":"mark","value":8}],[{"key":"day","value":11},{"key":"mark","value":12}],[{"key":"day","value":12},{"key":"mark","value":6},{"key":"comment","value":"\u0437\u0430\u043c\u0435\u0447\u0430\u043d\u0438\u0435 \u043d\u0430 \u0443\u0440\u043e\u043a\u0435"}],[{"key":"day","value":14},{"key":"mark","value":5}],[{"key":"day","value":15},{"key":"mark","value":10}],[{"key":"day","value":16},{"key":"mark","value":7}],[{"key":"day","value":17},{"key":"mark","value":6}],[{"key":"day","value":20},{"key":"mark","value":12}],[{"key":"day","value":21},{"key":"mark","value":11},{"key":"comment","value":"\u0437\u0430\u043c\u0435\u0447\u0430\u043d\u0438\u0435 \u043d\u0430 \u0443\u0440\u043e\u043a\u0435"}],[{"key":"day","value":25},{"key":"mark","value":7}],[{"key":"day","value":30},{"key":"mark","value":3}]],"\u0406\u0441\u0442\u043e\u0440\u0456\u044f \u0423\u043a\u0440\u0430\u0457\u043d\u0438":[[{"key":"day","value":3},{"key":"mark","value":1}],[{"key":"day","value":9},{"key":"mark","value":5}],[{"key":"day","value":11},{"key":"mark","value":10}],[{"key":"day","value":12},{"key":"mark","value":4}],[{"key":"day","value":13},{"key":"mark","value":7}],[{"key":"day","value":17},{"key":"mark","value":2}],[{"key":"day","value":18},{"key":"mark","value":7},{"key":"comment","value":"\u0437\u0430\u043c\u0435\u0447\u0430\u043d\u0438\u0435 \u043d\u0430 \u0443\u0440\u043e\u043a\u0435"}],[{"key":"day","value":20},{"key":"mark","value":2}],[{"key":"day","value":21},{"key":"mark","value":11},{"key":"comment","value":"\u0437\u0430\u043c\u0435\u0447\u0430\u043d\u0438\u0435 \u043d\u0430 \u0443\u0440\u043e\u043a\u0435"}],[{"key":"day","value":23},{"key":"mark","value":11}],[{"key":"day","value":26},{"key":"mark","value":9},{"key":"comment","value":"\u0437\u0430\u043c\u0435\u0447\u0430\u043d\u0438\u0435 \u043d\u0430 \u0443\u0440\u043e\u043a\u0435"}],[{"key":"day","value":28},{"key":"mark","value":7},{"key":"comment","value":"\u0437\u0430\u043c\u0435\u0447\u0430\u043d\u0438\u0435 \u043d\u0430 \u0443\u0440\u043e\u043a\u0435"}],[{"key":"day","value":29},{"key":"mark","value":5}],[{"key":"day","value":30},{"key":"mark","value":11},{"key":"comment","value":"\u0437\u0430\u043c\u0435\u0447\u0430\u043d\u0438\u0435 \u043d\u0430 \u0443\u0440\u043e\u043a\u0435"}]],"\u041f\u0440\u0430\u0432\u043e\u0437\u043d\u0430\u0432\u0441\u0442\u0432\u043e":[[{"key":"day","value":1},{"key":"mark","value":5}],[{"key":"day","value":4},{"key":"mark","value":4}],[{"key":"day","value":6},{"key":"mark","value":10},{"key":"comment","value":"\u0437\u0430\u043c\u0435\u0447\u0430\u043d\u0438\u0435 \u043d\u0430 \u0443\u0440\u043e\u043a\u0435"}],[{"key":"day","value":8},{"key":"mark","value":8}],[{"key":"day","value":9},{"key":"mark","value":5},{"key":"comment","value":"\u0437\u0430\u043c\u0435\u0447\u0430\u043d\u0438\u0435 \u043d\u0430 \u0443\u0440\u043e\u043a\u0435"}],[{"key":"day","value":10},{"key":"mark","value":10}],[{"key":"day","value":11},{"key":"mark","value":9},{"key":"comment","value":"\u0437\u0430\u043c\u0435\u0447\u0430\u043d\u0438\u0435 \u043d\u0430 \u0443\u0440\u043e\u043a\u0435"}],[{"key":"day","value":16},{"key":"mark","value":2},{"key":"comment","value":"\u0437\u0430\u043c\u0435\u0447\u0430\u043d\u0438\u0435 \u043d\u0430 \u0443\u0440\u043e\u043a\u0435"}],[{"key":"day","value":17},{"key":"mark","value":8},{"key":"comment","value":"\u0437\u0430\u043c\u0435\u0447\u0430\u043d\u0438\u0435 \u043d\u0430 \u0443\u0440\u043e\u043a\u0435"}],[{"key":"day","value":18},{"key":"mark","value":1}],[{"key":"day","value":19},{"key":"mark","value":12}],[{"key":"day","value":21},{"key":"mark","value":3},{"key":"comment","value":"\u0437\u0430\u043c\u0435\u0447\u0430\u043d\u0438\u0435 \u043d\u0430 \u0443\u0440\u043e\u043a\u0435"}],[{"key":"day","value":23},{"key":"mark","value":11}],[{"key":"day","value":24},{"key":"mark","value":11},{"key":"comment","value":"\u0437\u0430\u043c\u0435\u0447\u0430\u043d\u0438\u0435 \u043d\u0430 \u0443\u0440\u043e\u043a\u0435"}],[{"key":"day","value":27},{"key":"mark","value":5},{"key":"comment","value":"\u0437\u0430\u043c\u0435\u0447\u0430\u043d\u0438\u0435 \u043d\u0430 \u0443\u0440\u043e\u043a\u0435"}],[{"key":"day","value":29},{"key":"mark","value":10}],[{"key":"day","value":31},{"key":"mark","value":10},{"key":"comment","value":"\u0437\u0430\u043c\u0435\u0447\u0430\u043d\u0438\u0435 \u043d\u0430 \u0443\u0440\u043e\u043a\u0435"}]],"\u0424\u0456\u0437\u0438\u043a\u0430":[[{"key":"day","value":3},{"key":"mark","value":11}],[{"key":"day","value":5},{"key":"mark","value":6}],[{"key":"day","value":6},{"key":"mark","value":1}],[{"key":"day","value":8},{"key":"mark","value":12},{"key":"comment","value":"\u0437\u0430\u043c\u0435\u0447\u0430\u043d\u0438\u0435 \u043d\u0430 \u0443\u0440\u043e\u043a\u0435"}],[{"key":"day","value":9},{"key":"mark","value":1},{"key":"comment","value":"\u0437\u0430\u043c\u0435\u0447\u0430\u043d\u0438\u0435 \u043d\u0430 \u0443\u0440\u043e\u043a\u0435"}],[{"key":"day","value":11},{"key":"mark","value":4},{"key":"comment","value":"\u0437\u0430\u043c\u0435\u0447\u0430\u043d\u0438\u0435 \u043d\u0430 \u0443\u0440\u043e\u043a\u0435"}],[{"key":"day","value":13},{"key":"mark","value":11}],[{"key":"day","value":14},{"key":"mark","value":6},{"key":"comment","value":"\u0437\u0430\u043c\u0435\u0447\u0430\u043d\u0438\u0435 \u043d\u0430 \u0443\u0440\u043e\u043a\u0435"}],[{"key":"day","value":18},{"key":"mark","value":11},{"key":"comment","value":"\u0437\u0430\u043c\u0435\u0447\u0430\u043d\u0438\u0435 \u043d\u0430 \u0443\u0440\u043e\u043a\u0435"}],[{"key":"day","value":20},{"key":"mark","value":6},{"key":"comment","value":"\u0437\u0430\u043c\u0435\u0447\u0430\u043d\u0438\u0435 \u043d\u0430 \u0443\u0440\u043e\u043a\u0435"}],[{"key":"day","value":21},{"key":"mark","value":6},{"key":"comment","value":"\u0437\u0430\u043c\u0435\u0447\u0430\u043d\u0438\u0435 \u043d\u0430 \u0443\u0440\u043e\u043a\u0435"}],[{"key":"day","value":22},{"key":"mark","value":4},{"key":"comment","value":"\u0437\u0430\u043c\u0435\u0447\u0430\u043d\u0438\u0435 \u043d\u0430 \u0443\u0440\u043e\u043a\u0435"}],[{"key":"day","value":24},{"key":"mark","value":5}],[{"key":"day","value":28},{"key":"mark","value":8}],[{"key":"day","value":29},{"key":"mark","value":4},{"key":"comment","value":"\u0437\u0430\u043c\u0435\u0447\u0430\u043d\u0438\u0435 \u043d\u0430 \u0443\u0440\u043e\u043a\u0435"}],[{"key":"day","value":30},{"key":"mark","value":5},{"key":"comment","value":"\u0437\u0430\u043c\u0435\u0447\u0430\u043d\u0438\u0435 \u043d\u0430 \u0443\u0440\u043e\u043a\u0435"}]],"\u0425\u0456\u043c\u0456\u044f":[[{"key":"day","value":1},{"key":"mark","value":12}],[{"key":"day","value":5},{"key":"mark","value":6}],[{"key":"day","value":6},{"key":"mark","value":8}],[{"key":"day","value":8},{"key":"mark","value":12},{"key":"comment","value":"\u0437\u0430\u043c\u0435\u0447\u0430\u043d\u0438\u0435 \u043d\u0430 \u0443\u0440\u043e\u043a\u0435"}],[{"key":"day","value":12},{"key":"mark","value":3}],[{"key":"day","value":13},{"key":"mark","value":8},{"key":"comment","value":"\u0437\u0430\u043c\u0435\u0447\u0430\u043d\u0438\u0435 \u043d\u0430 \u0443\u0440\u043e\u043a\u0435"}],[{"key":"day","value":15},{"key":"mark","value":7},{"key":"comment","value":"\u0437\u0430\u043c\u0435\u0447\u0430\u043d\u0438\u0435 \u043d\u0430 \u0443\u0440\u043e\u043a\u0435"}],[{"key":"day","value":17},{"key":"mark","value":7}],[{"key":"day","value":18},{"key":"mark","value":3}],[{"key":"day","value":23},{"key":"mark","value":2},{"key":"comment","value":"\u0437\u0430\u043c\u0435\u0447\u0430\u043d\u0438\u0435 \u043d\u0430 \u0443\u0440\u043e\u043a\u0435"}],[{"key":"day","value":25},{"key":"mark","value":12}],[{"key":"day","value":26},{"key":"mark","value":6},{"key":"comment","value":"\u0437\u0430\u043c\u0435\u0447\u0430\u043d\u0438\u0435 \u043d\u0430 \u0443\u0440\u043e\u043a\u0435"}],[{"key":"day","value":27},{"key":"mark","value":6}],[{"key":"day","value":28},{"key":"mark","value":6},{"key":"comment","value":"\u0437\u0430\u043c\u0435\u0447\u0430\u043d\u0438\u0435 \u043d\u0430 \u0443\u0440\u043e\u043a\u0435"}],[{"key":"day","value":30},{"key":"mark","value":12}],[{"key":"day","value":31},{"key":"mark","value":1}]]},"homework":[[{"key":"day","value":1},{"key":"note","value":"\u0434\u0437 \u0443\u0440\u043e\u043a\u0430"}],[{"key":"day","value":3},{"key":"note","value":"\u0434\u0437 \u0443\u0440\u043e\u043a\u0430"}],[{"key":"day","value":4},{"key":"note","value":"\u0434\u0437 \u0443\u0440\u043e\u043a\u0430"}],[{"key":"day","value":5},{"key":"note","value":"\u0434\u0437 \u0443\u0440\u043e\u043a\u0430"}],[{"key":"day","value":6},{"key":"note","value":"\u0434\u0437 \u0443\u0440\u043e\u043a\u0430"}],[{"key":"day","value":8},{"key":"note","value":"\u0434\u0437 \u0443\u0440\u043e\u043a\u0430"}],[{"key":"day","value":16},{"key":"note","value":"\u0434\u0437 \u0443\u0440\u043e\u043a\u0430"}],[{"key":"day","value":17},{"key":"note","value":"\u0434\u0437 \u0443\u0440\u043e\u043a\u0430"}],[{"key":"day","value":19},{"key":"note","value":"\u0434\u0437 \u0443\u0440\u043e\u043a\u0430"}],[{"key":"day","value":21},{"key":"note","value":"\u0434\u0437 \u0443\u0440\u043e\u043a\u0430"}],[{"key":"day","value":24},{"key":"note","value":"\u0434\u0437 \u0443\u0440\u043e\u043a\u0430"}],[{"key":"day","value":26},{"key":"note","value":"\u0434\u0437 \u0443\u0440\u043e\u043a\u0430"}],[{"key":"day","value":27},{"key":"note","value":"\u0434\u0437 \u0443\u0440\u043e\u043a\u0430"}],[{"key":"day","value":29},{"key":"note","value":"\u0434\u0437 \u0443\u0440\u043e\u043a\u0430"}],[{"key":"day","value":30},{"key":"note","value":"\u0434\u0437 \u0443\u0440\u043e\u043a\u0430"}]]},"code":202,"errors":["Error message 1","Error message 2","Error message 3"]}